cslx/__init__.py
cslx/_version.py
cslx/handlers.py
cslx/labextension/package.json
cslx/labextension/static/454.fdbfc372571cb433929e.js
cslx/labextension/static/728.6e199085389e74601a49.js
cslx/labextension/static/remoteEntry.63f77b410c092806cfbe.js
cslx/labextension/static/style.js
cslx/labextension/static/third-party-licenses.json
cslx-0.1.1.data/data/share/jupyter/labextensions/cslx/package.json
cslx-0.1.1.data/data/share/jupyter/labextensions/cslx/static/454.fdbfc372571cb433929e.js
cslx-0.1.1.data/data/share/jupyter/labextensions/cslx/static/728.6e199085389e74601a49.js
cslx-0.1.1.data/data/share/jupyter/labextensions/cslx/static/remoteEntry.63f77b410c092806cfbe.js
cslx-0.1.1.data/data/share/jupyter/labextensions/cslx/static/style.js
cslx-0.1.1.data/data/share/jupyter/labextensions/cslx/static/third-party-licenses.json
cslx-0.1.1.data/data/share/jupyter/labextensions/cslx/install.json
cslx-0.1.1.dist-info/METADATA
cslx-0.1.1.dist-info/WHEEL
cslx-0.1.1.dist-info/licenses/LICENSE
cslx-0.1.1.dist-info/RECORD
