Metadata-Version: 2.4
Name: cslx
Version: 0.1.1
Summary: A JupyterLab extension for Cybershuttle
Project-URL: Homepage, https://github.com/cyber-shuttle/cybershuttle-jupyter-extension
Project-URL: Bug Tracker, https://github.com/cyber-shuttle/cybershuttle-jupyter-extension/issues
Project-URL: Repository, https://github.com/cyber-shuttle/cybershuttle-jupyter-extension.git
Author-email: Dimuthu Wannipurage <dimuthuw@gatech.edu>
License: BSD 3-Clause License
License-File: LICENSE
Keywords: jupyter,jupyterlab,jupyterlab-extension
Classifier: Framework :: Jupyter
Classifier: Framework :: Jupyter :: JupyterLab
Classifier: Framework :: Jupyter :: JupyterLab :: 4
Classifier: Framework :: Jupyter :: JupyterLab :: Extensions
Classifier: Framework :: Jupyter :: JupyterLab :: Extensions :: Prebuilt
Classifier: License :: OSI Approved :: BSD License
Classifier: Programming Language :: Python
Classifier: Programming Language :: Python :: 3
Classifier: Programming Language :: Python :: 3.9
Classifier: Programming Language :: Python :: 3.10
Classifier: Programming Language :: Python :: 3.11
Classifier: Programming Language :: Python :: 3.12
Classifier: Programming Language :: Python :: 3.13
Requires-Python: >=3.9
